yt_transcript/__init__.py
yt_transcript/__main__.py
yt_transcript/cli.py
yt_transcript/summarizer.py
yt_transcript/transcript_fetcher.py
yt_transcript-0.1.4.dist-info/METADATA
yt_transcript-0.1.4.dist-info/WHEEL
yt_transcript-0.1.4.dist-info/entry_points.txt
yt_transcript-0.1.4.dist-info/RECORD
