Metadata-Version: 2.4
Name: yt-transcript
Version: 0.1.4
Summary: A command-line tool to fetch, cache, and summarize YouTube video transcripts
Project-URL: Homepage, https://github.com/lawwu/yt-transcript
Project-URL: Bug Tracker, https://github.com/lawwu/yt-transcript/issues
Author: Lawrence Wu
License: MIT
Classifier: License :: OSI Approved :: MIT License
Classifier: Operating System :: OS Independent
Classifier: Programming Language :: Python :: 3
Requires-Python: >=3.9
Requires-Dist: click
Requires-Dist: openai
Requires-Dist: requests
Requires-Dist: youtube-transcript-api
Requires-Dist: yt-dlp
Provides-Extra: dev
Requires-Dist: pre-commit; extra == 'dev'
Requires-Dist: pytest; extra == 'dev'
Requires-Dist: ruff; extra == 'dev'
